setup.py
django_dbconf/__init__.py
django_dbconf/admin.py
django_dbconf/conf.py
django_dbconf/models.py
django_dbconf.egg-info/PKG-INFO
django_dbconf.egg-info/SOURCES.txt
django_dbconf.egg-info/dependency_links.txt
django_dbconf.egg-info/not-zip-safe
django_dbconf.egg-info/requires.txt
django_dbconf.egg-info/top_level.txt