Metadata-Version: 1.0
Name: django-dbconf
Version: 0.1
Summary: Simple helper to save settings in a database and efficient access to this data through cache.
Home-page: https://github.com/niwibe/django-dbconf
Author: Andrei Antoukh
Author-email: niwi@niwi.be
License: BSD
Platform: OS Independent
Classifier: Development Status :: 4 - Beta
Classifier: Framework :: Django
Classifier: Intended Audience :: Developers
Classifier: License :: OSI Approved :: BSD License
Classifier: Operating System :: OS Independent
Classifier: Programming Language :: Python
Classifier: Topic :: Internet :: WWW/HTTP
